{"cameraMode":{"drawMode":0,"name":"Shaded","section":"Shading Mode"},"sceneLighting":true,"audioPlay":false,"sceneViewState":{"showFog":true,"showMaterialUpdate":false,"showSkybox":true,"showFlares":true,"showImageEffects":true,"showParticleSystems":true},"in2DMode":false,"pivot":{"x":-0.5495266914367676,"y":3.4353628158569338,"z":0.19327831268310548},"rotation":{"x":-0.18417248129844666,"y":0.10504300892353058,"z":-0.01980009488761425,"w":-0.9770641922950745},"size":6.3698410987854,"orthographic":false}